{
  "iceServers": [
    {
      "urls": "stun:stun.l.google.com:19302"
    },
    {
      "urls": [
        "stun:stun.cloudflare.com:3478",
        "turn:turn.cloudflare.com:3478?transport=udp",
        "turn:turn.cloudflare.com:3478?transport=tcp",
        "turns:turn.cloudflare.com:5349?transport=tcp"
      ],
      "username": "g0331b6aacde3b212712c4b75208e00df52493cffa52f7687f082c87cec69241",
      "credential": "03e2cc30d633c02ad5ba7ba65c265745c9168deff5d011a31c17149d3a70a1a5"
    }
  ]
}
